twsca/__init__.py
twsca/__main__.py
twsca/_version.py
twsca/analysis.py
twsca/cli.py
twsca/config.py
twsca/dtw.py
twsca/smoothing.py
twsca/spectral.py
twsca/utils.py
twsca-0.3.0.dist-info/licenses/LICENSE
twsca-0.3.0.dist-info/METADATA
twsca-0.3.0.dist-info/WHEEL
twsca-0.3.0.dist-info/top_level.txt
twsca-0.3.0.dist-info/RECORD
