Metadata-Version: 2.4
Name: twsca
Version: 0.3.0
Summary: Time-Warped Spectral Correlation Analysis
License: MIT License
Project-URL: Homepage, https://github.com/TheGameStopsNow/twsca
Project-URL: Documentation, https://twsca.readthedocs.io
Project-URL: Repository, https://github.com/TheGameStopsNow/twsca.git
Project-URL: Issues, https://github.com/TheGameStopsNow/twsca/issues
Keywords: time-series,analysis,correlation,spectral-analysis,dtw
Classifier: Development Status :: 4 - Beta
Classifier: Intended Audience :: Science/Research
Classifier: License :: OSI Approved :: MIT License
Classifier: Programming Language :: Python :: 3
Classifier: Programming Language :: Python :: 3.8
Classifier: Programming Language :: Python :: 3.9
Classifier: Programming Language :: Python :: 3.10
Classifier: Programming Language :: Python :: 3.11
Classifier: Topic :: Scientific/Engineering
Requires-Python: >=3.8
License-File: LICENSE
Requires-Dist: numpy>=1.20.0
Requires-Dist: scipy>=1.7.0
Requires-Dist: matplotlib>=3.4.0
Requires-Dist: seaborn>=0.11.0
Requires-Dist: tqdm>=4.65.0
Requires-Dist: joblib>=1.1.0
Requires-Dist: plotly>=5.13.0
Requires-Dist: pandas>=1.3.0
Requires-Dist: scikit-learn>=1.0.0
Provides-Extra: interactive
Requires-Dist: jupyter>=1.0.0; extra == "interactive"
Requires-Dist: ipywidgets>=8.0.0; extra == "interactive"
Requires-Dist: nbformat>=5.0.0; extra == "interactive"
Requires-Dist: plotly>=5.13.0; extra == "interactive"
Provides-Extra: dev
Requires-Dist: pytest>=7.0.0; extra == "dev"
Requires-Dist: pytest-cov>=4.0.0; extra == "dev"
Requires-Dist: black>=22.0.0; extra == "dev"
Requires-Dist: isort>=5.0.0; extra == "dev"
Requires-Dist: mypy>=1.0.0; extra == "dev"
Requires-Dist: flake8>=6.0.0; extra == "dev"
Requires-Dist: sphinx>=4.0.0; extra == "dev"
Requires-Dist: sphinx-rtd-theme>=1.0.0; extra == "dev"
Provides-Extra: docs
Requires-Dist: sphinx>=4.0.0; extra == "docs"
Requires-Dist: sphinx-rtd-theme>=1.0.0; extra == "docs"
Requires-Dist: nbsphinx>=0.8.0; extra == "docs"
Requires-Dist: ipykernel>=6.0.0; extra == "docs"
Dynamic: license-file
